Multi_Layer_Kernel_Machine/DataSplitting.py
Multi_Layer_Kernel_Machine/Fitting.py
Multi_Layer_Kernel_Machine/GenerateSplit.py
Multi_Layer_Kernel_Machine/Mydataset.py
Multi_Layer_Kernel_Machine/RandomFeature.py
Multi_Layer_Kernel_Machine/Structure.py
Multi_Layer_Kernel_Machine/__init__.py
multi_layer_kernel_machine-1.0.1.dist-info/METADATA
multi_layer_kernel_machine-1.0.1.dist-info/WHEEL
multi_layer_kernel_machine-1.0.1.dist-info/licenses/LICENSE.txt
multi_layer_kernel_machine-1.0.1.dist-info/RECORD
